qbraid_core/__init__.py
qbraid_core/_compat.py
qbraid_core/_import.py
qbraid_core/_version.py
qbraid_core/annotations.py
qbraid_core/client.py
qbraid_core/config.py
qbraid_core/context.py
qbraid_core/decimal.py
qbraid_core/exceptions.py
qbraid_core/py.typed
qbraid_core/registry.py
qbraid_core/retry.py
qbraid_core/sessions.py
qbraid_core/services/__init__.py
qbraid_core/services/chat/__init__.py
qbraid_core/services/chat/client.py
qbraid_core/services/chat/exceptions.py
qbraid_core/services/environments/__init__.py
qbraid_core/services/environments/client.py
qbraid_core/services/environments/create.py
qbraid_core/services/environments/exceptions.py
qbraid_core/services/environments/kernels.py
qbraid_core/services/environments/magic.py
qbraid_core/services/environments/paths.py
qbraid_core/services/environments/schema.py
qbraid_core/services/environments/state.py
qbraid_core/services/environments/validate.py
qbraid_core/services/mcp/__init__.py
qbraid_core/services/mcp/client.py
qbraid_core/services/mcp/discovery.py
qbraid_core/services/mcp/router.py
qbraid_core/services/quantum/__init__.py
qbraid_core/services/quantum/adapter.py
qbraid_core/services/quantum/client.py
qbraid_core/services/quantum/exceptions.py
qbraid_core/services/quantum/proxy.py
qbraid_core/services/quantum/proxy_braket.py
qbraid_core/services/quantum/runner.py
qbraid_core/services/runtime/__init__.py
qbraid_core/services/runtime/client.py
qbraid_core/services/runtime/exceptions.py
qbraid_core/services/runtime/schemas/__init__.py
qbraid_core/services/runtime/schemas/device.py
qbraid_core/services/runtime/schemas/enums.py
qbraid_core/services/runtime/schemas/job.py
qbraid_core/services/runtime/schemas/result.py
qbraid_core/services/storage/__init__.py
qbraid_core/services/storage/client.py
qbraid_core/services/storage/disk_usage_client.py
qbraid_core/services/storage/exceptions.py
qbraid_core/services/storage/types.py
qbraid_core/system/__init__.py
qbraid_core/system/exceptions.py
qbraid_core-0.1.49.dist-info/licenses/LICENSE
qbraid_core-0.1.49.dist-info/METADATA
qbraid_core-0.1.49.dist-info/WHEEL
qbraid_core-0.1.49.dist-info/top_level.txt
qbraid_core-0.1.49.dist-info/RECORD
