Metadata-Version: 2.4
Name: qbraid-core
Version: 0.1.49
Summary: Python library with core abstractions for software development in the qBraid ecosystem.
Author: qBraid Development Team
Author-email: contact@qbraid.com
License: Proprietary
Project-URL: Homepage, https://docs.qbraid.com/core
Project-URL: Documentation, https://qbraid.github.io/qbraid-core/
Project-URL: Bug Tracker, https://github.com/qBraid/community/issues
Project-URL: Discord, https://discord.gg/KugF6Cnncm
Keywords: qbraid,quantum,cloud
Classifier: Development Status :: 5 - Production/Stable
Classifier: Intended Audience :: Developers
Classifier: Intended Audience :: System Administrators
Classifier: Natural Language :: English
Classifier: Programming Language :: Python
Classifier: Programming Language :: Python :: 3
Classifier: Programming Language :: Python :: 3.9
Classifier: Programming Language :: Python :: 3.10
Classifier: Programming Language :: Python :: 3.11
Classifier: Programming Language :: Python :: 3.12
Classifier: Programming Language :: Python :: 3.13
Classifier: Programming Language :: Python :: 3.14
Classifier: Programming Language :: Python :: 3 :: Only
Classifier: Topic :: Software Development
Classifier: Topic :: Scientific/Engineering
Classifier: Topic :: Scientific/Engineering :: Physics
Classifier: Typing :: Typed
Classifier: Operating System :: Microsoft :: Windows
Classifier: Operating System :: POSIX
Classifier: Operating System :: Unix
Classifier: Operating System :: MacOS
Requires-Python: >=3.9
License-File: LICENSE
Requires-Dist: requests
Requires-Dist: urllib3
Requires-Dist: packaging
Requires-Dist: pydantic>2.0.0
Provides-Extra: runner
Requires-Dist: numpy; extra == "runner"
Requires-Dist: psutil; extra == "runner"
Provides-Extra: environments
Requires-Dist: jupyter_client>=7.1.0; extra == "environments"
Requires-Dist: ipython; extra == "environments"
Requires-Dist: pyyaml>6.0.0; extra == "environments"
Requires-Dist: ipykernel; extra == "environments"
Provides-Extra: envs
Requires-Dist: jupyter_client>=7.1.0; extra == "envs"
Requires-Dist: ipython; extra == "envs"
Requires-Dist: pyyaml>6.0.0; extra == "envs"
Requires-Dist: ipykernel; extra == "envs"
Provides-Extra: mcp
Requires-Dist: websockets>=11.0; extra == "mcp"
Provides-Extra: test
Requires-Dist: pytest; extra == "test"
Requires-Dist: pytest-cov; extra == "test"
Requires-Dist: pytest-asyncio; extra == "test"
Provides-Extra: docs
Requires-Dist: sphinx<8.3.0,>=7.2.6; extra == "docs"
Requires-Dist: sphinx-rtd-theme<3.1,>=1.3; extra == "docs"
Requires-Dist: sphinx-autodoc-typehints<3.2,>=1.24; extra == "docs"
Requires-Dist: docutils<0.23; extra == "docs"
Requires-Dist: sphinx-copybutton; extra == "docs"
Requires-Dist: sphinx-pydantic; extra == "docs"
Dynamic: license-file
